SpatialTools-2.1.15.data/scripts/run_app.py
SpatialTools-2.1.15.data/scripts/run_spatial_tools
spatial_tools/__init__.py
spatial_tools/_len_obj.py
spatial_tools/demo.py
spatial_tools/demo_v1.py
spatial_tools/plotting.py
spatial_tools/run_app.py
spatial_tools/spatial_tools.py
spatial_tools/spatial_tools_origin.py
spatial_tools/test.py
spatial_tools/test2.py
spatial_tools/utils.py
spatial_tools/vision.py
SpatialTools-2.1.15.dist-info/METADATA
SpatialTools-2.1.15.dist-info/WHEEL
SpatialTools-2.1.15.dist-info/top_level.txt
SpatialTools-2.1.15.dist-info/RECORD
